amati/__init__.py
amati/_error_handler.py
amati/_logging.py
amati/_references.py
amati/_resolve_forward_references.py
amati/amati.py
amati/exceptions.py
amati/file_handler.py
amati/model_validators.py
amati/py.typed
amati/_data/http_status_code.py
amati/_data/iso9110.py
amati/_data/media_types.py
amati/_data/refresh.py
amati/_data/schemes.py
amati/_data/spdx_licences.py
amati/_data/tlds.py
amati/_data/files/http-status-codes.json
amati/_data/files/iso9110.json
amati/_data/files/media-types.json
amati/_data/files/schemes.json
amati/_data/files/spdx-licences.json
amati/_data/files/tlds.json
amati/fields/__init__.py
amati/fields/_custom_types.py
amati/fields/commonmark.py
amati/fields/email.py
amati/fields/http_status_codes.py
amati/fields/iso9110.py
amati/fields/json.py
amati/fields/media.py
amati/fields/oas.py
amati/fields/spdx_licences.py
amati/fields/uri.py
amati/grammars/oas.py
amati/grammars/rfc6901.py
amati/grammars/rfc7159.py
amati/validators/__init__.py
amati/validators/_discriminators.py
amati/validators/generic.py
amati/validators/oas304.py
amati/validators/oas311.py
amati-0.3.29.dist-info/METADATA
amati-0.3.29.dist-info/WHEEL
amati-0.3.29.dist-info/entry_points.txt
amati-0.3.29.dist-info/licenses/LICENSE
amati-0.3.29.dist-info/RECORD
