Metadata-Version: 2.4
Name: amati
Version: 0.3.29
Summary: Validates that a .yaml or .json file conforms to the OpenAPI Specifications 3.x.
Project-URL: Homepage, https://github.com/gwyli/amati
Project-URL: Issues, https://github.com/gwyli/amati/issues
Author-email: Ben <2551337+ben-alexander@users.noreply.github.com>
License-File: LICENSE
Keywords: json,openapi,openapi3,openapi3.0,openapi3.1,swagger,validation,validator,yaml
Classifier: Development Status :: 3 - Alpha
Classifier: Intended Audience :: Developers
Classifier: License :: OSI Approved :: MIT License
Classifier: Programming Language :: Python :: 3 :: Only
Classifier: Programming Language :: Python :: 3.14
Classifier: Topic :: Internet :: WWW/HTTP :: Dynamic Content
Classifier: Topic :: Software Development
Classifier: Topic :: Software Development :: Build Tools
Classifier: Topic :: Software Development :: Documentation
Classifier: Topic :: Software Development :: Quality Assurance
Classifier: Topic :: Software Development :: Testing :: Acceptance
Classifier: Typing :: Typed
Requires-Python: >=3.14
Requires-Dist: abnf>=2.3.1
Requires-Dist: bs4>=0.0.2
Requires-Dist: idna>=3.10
Requires-Dist: jinja2>=3.1.6
Requires-Dist: jsonschema>=4.24.0
Requires-Dist: loguru>=0.7.3
Requires-Dist: pydantic-core>=2.41.5
Requires-Dist: pydantic>=2.12.5
Requires-Dist: pyyaml>=6.0.3
Requires-Dist: requests>=2.32.4
